miniexact/__init__.py
miniexact/_pyminiexact.pyd
miniexact-1.6.data/scripts/miniexact.exe
miniexact-1.6.dist-info/METADATA
miniexact-1.6.dist-info/WHEEL
miniexact-1.6.dist-info/licenses/LICENSE.md
miniexact-1.6.dist-info/RECORD
