Metadata-Version: 2.4
Name: miniexact
Version: 1.6
Summary: This is the MiniExact exact cover solver, implementing Donald Knuth's Algorithm X, C, and M using the Dancing Links technique.
Author-Email: Max Heisinger <mail+pypi@maxheisinger.at>
License-Expression: BSD-3-Clause
Project-URL: changelog, https://github.com/miniexact/miniexact/blob/main/CHANGELOG.md
Project-URL: homepage, https://github.com/miniexact/miniexact
Project-URL: repository, https://github.com/miniexact/miniexact.git
Requires-Python: >=3.8
